setup.py
DPFM/__init__.py
DPFM/data_process.py
DPFM.egg-info/PKG-INFO
DPFM.egg-info/SOURCES.txt
DPFM.egg-info/dependency_links.txt
DPFM.egg-info/top_level.txt