Metadata-Version: 2.1
Name: DPFM
Version: 0.0.5
Summary: Data processing for marine
Home-page: https://github.com/
License: UNKNOWN
Platform: UNKNOWN
Classifier: Programming Language :: Python :: 3
Classifier: License :: OSI Approved :: MIT License
Classifier: Operating System :: OS Independent
